llama_tools/__init__.py
llama_tools/postprocess.py
llama_tools/preprocess.py
llama_tools-0.1.21.dist-info/WHEEL
llama_tools-0.1.21.dist-info/METADATA
llama_tools-0.1.21.dist-info/RECORD
